LICENSE
MANIFEST.in
README.rst
setup.py
wp-config-sample.cfg
python_wordpress_xmlrpc.egg-info/PKG-INFO
python_wordpress_xmlrpc.egg-info/SOURCES.txt
python_wordpress_xmlrpc.egg-info/dependency_links.txt
python_wordpress_xmlrpc.egg-info/top_level.txt
wordpress_xmlrpc/__init__.py
wordpress_xmlrpc/base.py
wordpress_xmlrpc/compat.py
wordpress_xmlrpc/exceptions.py
wordpress_xmlrpc/fieldmaps.py
wordpress_xmlrpc/transports.py
wordpress_xmlrpc/wordpress.py
wordpress_xmlrpc/methods/__init__.py
wordpress_xmlrpc/methods/comments.py
wordpress_xmlrpc/methods/demo.py
wordpress_xmlrpc/methods/media.py
wordpress_xmlrpc/methods/options.py
wordpress_xmlrpc/methods/pages.py
wordpress_xmlrpc/methods/posts.py
wordpress_xmlrpc/methods/taxonomies.py
wordpress_xmlrpc/methods/users.py