Metadata-Version: 1.1
Name: python-wordpress-xmlrpc
Version: 2.3
Summary: WordPress XML-RPC API Integration Library
Home-page: https://github.com/maxcutler/python-wordpress-xmlrpc/
Author: Max Cutler
Author-email: max@maxcutler.com
License: BSD
Platform: UNKNOWN
Classifier: Programming Language :: Python
Classifier: License :: OSI Approved :: BSD License
Classifier: Operating System :: OS Independent
Classifier: Development Status :: 4 - Beta
Classifier: Intended Audience :: Developers
Classifier: Environment :: Console
Classifier: Environment :: Web Environment
Classifier: Topic :: Software Development :: Libraries :: Python Modules
Classifier: Topic :: Internet :: WWW/HTTP :: Site Management
Classifier: Topic :: Utilities
Classifier: Natural Language :: English
